yangson_inventory_builder/__init__.py
yangson_inventory_builder/inventory_builder.py
yangson_inventory_builder/inventory_classes.py
yangson_inventory_builder-0.1.3.dist-info/LICENSE
yangson_inventory_builder-0.1.3.dist-info/METADATA
yangson_inventory_builder-0.1.3.dist-info/WHEEL
yangson_inventory_builder-0.1.3.dist-info/top_level.txt
yangson_inventory_builder-0.1.3.dist-info/RECORD
